uuRest/__init__.py
uuRest/common.py
uuRest/uuCommand.py
uuRest/uuRest.py
uuTS/__init__.py
uuTS/uuTS.py
uuTS-0.0.3.dist-info/LICENSE
uuTS-0.0.3.dist-info/METADATA
uuTS-0.0.3.dist-info/WHEEL
uuTS-0.0.3.dist-info/top_level.txt
uuTS-0.0.3.dist-info/RECORD
