Metadata-Version: 2.1
Name: uuTS
Version: 0.0.3
Summary: Unicorn Universe REST API (Unicorn Systems & Unicorn Application Framework)
Home-page: UNKNOWN
Author: jaromirsivic (Jaromir Sivic)
Author-email: <email@email.com>
License: UNKNOWN
Keywords: python,uuRest,Unicorn Systems,UAF,Unicorn Application Framework
Platform: UNKNOWN
Classifier: Development Status :: 1 - Planning
Classifier: Intended Audience :: Developers
Classifier: Programming Language :: Python :: 3
Classifier: Operating System :: Unix
Classifier: Operating System :: MacOS :: MacOS X
Classifier: Operating System :: Microsoft :: Windows
Requires-Dist: uuRest
